scaleinvariance/__init__.py
scaleinvariance/backend.py
scaleinvariance/analysis/__init__.py
scaleinvariance/analysis/haar_fluctuation.py
scaleinvariance/analysis/intermittency.py
scaleinvariance/analysis/spectral.py
scaleinvariance/analysis/structure_function.py
scaleinvariance/simulation/FIF.py
scaleinvariance/simulation/__init__.py
scaleinvariance/simulation/fbm.py
scaleinvariance/simulation/generalized_scale_invariance.py
scaleinvariance/utils/__init__.py
scaleinvariance-0.6.0.dist-info/METADATA
scaleinvariance-0.6.0.dist-info/WHEEL
scaleinvariance-0.6.0.dist-info/top_level.txt
scaleinvariance-0.6.0.dist-info/RECORD
