Metadata-Version: 2.4
Name: scaleinvariance
Version: 0.6.0
Summary: Simulation and analysis of multifractal fields
Author: Thomas DeWitt
License: MIT
Project-URL: Homepage, https://github.com/thomasdewitt/scaleinvariance
Classifier: Development Status :: 3 - Alpha
Classifier: Intended Audience :: Science/Research
Classifier: Programming Language :: Python :: 3
Classifier: Programming Language :: Python :: 3.8
Classifier: Programming Language :: Python :: 3.9
Classifier: Programming Language :: Python :: 3.10
Classifier: Programming Language :: Python :: 3.11
Requires-Python: >=3.8
Requires-Dist: numpy
Requires-Dist: scipy
Provides-Extra: torch
Requires-Dist: torch; extra == "torch"
Dynamic: requires-python
